sync_fifo.v
module sync_fifo
#(
    parameter DEPTH = 8, 
    parameter DWIDTH = 8
)

(
    input clk, 
    input rstn, //0=reset fifo and 1=normal operation

    input wr_en, //fifo writes data
    input rd_en, //fifo reads data

    input [7:0] din,
    output reg [7:0] dout,

    output full,
    output empty
);

reg [7:0] fifo [0:7];

reg [2:0] wptr;
reg [2:0] rptr;

reg [3:0] count;

always @(posedge clk) begin //write logic
    
    if(!rstn)
    begin
        wptr<=0; //start writing from 0 location again
    end

    else if(wr_en && !full) begin //write req fifo not full
        fifo[wptr]<=din;
        wptr<=wptr+1;
    end
end
always @(posedge clk)begin //read logic
    if(!rstn)
    begin
        rptr<=0;
        dout<=0;
    end

    else if(rd_en && !empty) begin 
        dout<=fifo[rptr];
        rptr<=rptr+1;
    end

    else if(!wr_en && rd_en && !empty)
    begin
        count <= count-1;
    end
end
    always @(posedge clk) begin
        if(!rstn) begin
            count<=0;
        end
        else if(wr_en && !rd_en && !full) begin
            count<=count+1;
        end
        end
        assign full=(count==8);
        assign empty=(count==0);
  
endmodule

tb.v
module tb;

reg clk;
reg rstn;
reg wr_en;
reg rd_en;
reg [7:0] din;
wire [7:0] dout;
wire full;
wire empty;

sync_fifo uut(clk, rstn, wr_en, rd_en, din, dout, full, empty);

always #5 clk=~clk;

initial begin
    clk=0;
    rstn=0;
    wr_en=0;
    rd_en=0;
    din=0;
end


initial begin
    $monitor("TIME=%0t wr=%0b rd=%0b din=%h dout=%h full=%0b empty=%0b", 
        $time, wr_en, rd_en, din, dout, full, empty);
    end

initial begin

    $dumpfile("dump.vcd");
    $dumpvars(0, tb);

end

initial begin
    #20 rstn=1;

    wr_en=1; din=8'h11; #10;
    din=8'h22; #10;
    din=8'h33; #10;
    wr_en=0;

    #10;

    rd_en=1; #30;
    rd_en=0;

    #10 wr_en = 1; din = 8'h44; rd_en = 1; #10;
    wr_en = 0; rd_en = 0;

    #50 $finish;

    
end
endmodule

dump.vcd
$date
	Sat May 23 12:36:13 2026
$end
$version
	Icarus Verilog
$end
$timescale
	1s
$end
$scope module tb $end
$var wire 1 ! full $end
$var wire 1 " empty $end
$var wire 8 # dout [7:0] $end
$var reg 1 $ clk $end
$var reg 8 % din [7:0] $end
$var reg 1 & rd_en $end
$var reg 1 ' rstn $end
$var reg 1 ( wr_en $end
$scope module uut $end
$var wire 1 $ clk $end
$var wire 8 ) din [7:0] $end
$var wire 1 & rd_en $end
$var wire 1 ' rstn $end
$var wire 1 ( wr_en $end
$var wire 1 ! full $end
$var wire 1 " empty $end
$var parameter 32 * DEPTH $end
$var parameter 32 + DWIDTH $end
$var reg 4 , count [3:0] $end
$var reg 8 - dout [7:0] $end
$var reg 3 . rptr [2:0] $end
$var reg 3 / wptr [2:0] $end
$upscope $end
$upscope $end
$enddefinitions $end
$comment Show the parameter values. $end
$dumpall
b1000 +
b1000 *
$end
#0
$dumpvars
bx /
bx .
bx -
bx ,
b0 )
0(
0'
0&
b0 %
0$
bx #
x"
x!
$end
#5
b0 /
b0 #
b0 -
b0 .
0!
1"
b0 ,
1$
#10
0$
#15
1$
#20
0$
b10001 %
b10001 )
1(
1'
#25
b1 /
0"
b1 ,
1$
#30
0$
b100010 %
b100010 )
#35
b10 ,
b10 /
1$
#40
0$
b110011 %
b110011 )
#45
b11 /
b11 ,
1$
#50
0$
0(
#55
1$
#60
0$
1&
#65
b1 .
b10001 #
b10001 -
1$
#70
0$
#75
b10 .
b100010 #
b100010 -
1$
#80
0$
#85
b11 .
b110011 #
b110011 -
1$
#90
0$
0&
#95
1$
#100
0$
1&
b1000100 %
b1000100 )
1(
#105
b100 /
b100 .
bx #
bx -
1$
#110
0$
0&
0(
